README.rst
setup.cfg
setup.py
./__init__.py
./product.py
./product.xml
./tryton.cfg
./tests/__init__.py
./tests/test_product.py
./view/attribute_form.xml
./view/attribute_list.xml
./view/attribute_set_form.xml
./view/attribute_set_list.xml
./view/product_attribute_form.xml
./view/product_attribute_tree.xml
./view/product_form.xml
./view/template_form.xml
fio_product_attribute_strict.egg-info/PKG-INFO
fio_product_attribute_strict.egg-info/SOURCES.txt
fio_product_attribute_strict.egg-info/dependency_links.txt
fio_product_attribute_strict.egg-info/entry_points.txt
fio_product_attribute_strict.egg-info/not-zip-safe
fio_product_attribute_strict.egg-info/requires.txt
fio_product_attribute_strict.egg-info/top_level.txt